kicadcliwrapper/lib.py
kicadcliwrapper/main.py
kicadcliwrapper/generated/kicad_cli.py
kicadcliwrapper/generated/kicad_cli_l1.py
kicadcliwrapper/generated/kicad_cli_l2.py
kicadcliwrapper-1.1.1.dist-info/METADATA
kicadcliwrapper-1.1.1.dist-info/WHEEL
kicadcliwrapper-1.1.1.dist-info/licenses/LICENSE
kicadcliwrapper-1.1.1.dist-info/RECORD
