Metadata-Version: 2.4
Name: kicadcliwrapper
Version: 1.1.1
Summary: Kicad-CLI python bindings
Project-URL: Homepage, https://github.com/atopile/kicadcliwrapper
Project-URL: Repository, https://github.com/atopile/kicadcliwrapper
Project-URL: Bug Tracker, https://github.com/faebryk/kicadcliwrapper/issues
Author-email: Ioannis Papamanoglou <ioannis@atopile.io>, Matthew Wildoer <matt@atopile.io>, Narayan Powderly <narayan@atopile.io>
License: MIT
License-File: LICENSE
Classifier: License :: OSI Approved :: MIT License
Classifier: Operating System :: OS Independent
Classifier: Programming Language :: Python :: 3
Requires-Python: >=3.13
Requires-Dist: black>=24.4.2
Requires-Dist: typing-extensions>=4.6.3
